{
    "addresses": [
    {
        "country": {
            "isocode": "US",
            "name": "United States"
        },
        "firstName": "Mark",
        "formattedAddress": "17603 34th Place W, Line2, Washington, Lynnwood, 98037",
        "id": "8804776640535",
        "lastName": "Juckerberg",
        "line1": "17603 34th Place W",
        "line2": "Line2",
        "phone1": "(339)224-8782",
        "postalCode": "98037",
        "region": {
            "countryIso": "US",
            "isocode": "US-WA",
            "isocodeShort": "WA",
            "name": "Washington"
        },
        "shippingAddress": true,
        "title": "Mr.",
        "titleCode": "mr.",
        "town": "Lynnwood",
        "visibleInAddressBook": true
    },
    {
        "country": {
            "isocode": "US",
            "name": "United States"
        },
        "firstName": "Nana",
        "formattedAddress": "34th lace, Washington, Lynnwood, 98037",
        "id": "8804779786263",
        "lastName": "Patekar",
        "line1": "34th lace",
        "phone1": "(339)252-7482",
        "postalCode": "98037",
        "region": {
            "countryIso": "US",
            "isocode": "US-WA",
            "isocodeShort": "WA",
            "name": "Washington"
        },
        "shippingAddress": true,
        "title": "Mr.",
        "titleCode": "mr.",
        "town": "Lynnwood",
        "visibleInAddressBook": true
    },
    {
        "country": {
            "isocode": "US",
            "name": "United States"
        },
        "firstName": "Shahrukh",
        "formattedAddress": "34th Place, Washington, Lynnwood, 98037",
        "id": "8804779753495",
        "lastName": "Khan",
        "line1": "34th Place",
        "phone1": "(339)242-6384",
        "postalCode": "98037",
        "region": {
            "countryIso": "US",
            "isocode": "US-WA",
            "isocodeShort": "WA",
            "name": "Washington"
        },
        "shippingAddress": true,
        "title": "Mr.",
        "titleCode": "mr.",
        "town": "Lynnwood",
        "visibleInAddressBook": true
    },
    {
        "country": {
            "isocode": "US",
            "name": "United States"
        },
        "firstName": "Frank",
        "formattedAddress": "17603 34thPlace W, Line2, Washington, Lynnwood, 98037",
        "id": "8804743872535",
        "lastName": "Darwin",
        "line1": "17603 34thPlace W",
        "line2": "Line2",
        "phone1": "(339)224-8782",
        "postalCode": "98037",
        "region": {
            "countryIso": "US",
            "isocode": "US-WA",
            "isocodeShort": "WA",
            "name": "Washington"
        },
        "shippingAddress": true,
        "title": "Mr.",
        "titleCode": "mr.",
        "town": "Lynnwood",
        "visibleInAddressBook": true
    },
    {
        "country": {
            "isocode": "US",
            "name": "United States"
        },
        "firstName": "Chintu",
        "formattedAddress": "17603 34thPlace W, Line2, Washington, Lynnwood, 98037",
        "id": "8804743839767",
        "lastName": "Sahu",
        "line1": "17603 34thPlace W",
        "line2": "Line2",
        "phone1": "(339)224-8782",
        "postalCode": "98037",
        "region": {
            "countryIso": "US",
            "isocode": "US-WA",
            "isocodeShort": "WA",
            "name": "Washington"
        },
        "shippingAddress": true,
        "title": "Mr.",
        "titleCode": "mr.",
        "town": "Lynnwood",
        "visibleInAddressBook": true
    }
    ]
}
